pyispyb/__init__.py
pyispyb/__man__.py
pyispyb/config.py
pyispyb/app/__init__.py
pyispyb/app/extensions/__init__.py
pyispyb/app/extensions/api/__init__.py
pyispyb/app/extensions/api/api.py
pyispyb/app/extensions/api/http_exceptions.py
pyispyb/app/extensions/api/namespace.py
pyispyb/app/extensions/api/parameters.py
pyispyb/app/extensions/api/webargs_parser.py
pyispyb/app/extensions/auth/AbstractAuth.py
pyispyb/app/extensions/auth/DummyAuth.py
pyispyb/app/extensions/auth/EMBLAuth.py
pyispyb/app/extensions/auth/__init__.py
pyispyb/app/extensions/flask_sqlalchemy/__init__.py
pyispyb/app/extensions/logging/__init__.py
pyispyb/app/extensions/user_office_link/AbstractUserOfficeLink.py
pyispyb/app/extensions/user_office_link/DummyUserOfficeLink.py
pyispyb/app/extensions/user_office_link/SmisLink.py
pyispyb/app/extensions/user_office_link/__init__.py
pyispyb/app/routes/__init__.py
pyispyb/app/routes/auth.py
pyispyb/app/utils/__init__.py
pyispyb/connector/__init__.py
pyispyb/core/__init__.py
pyispyb/core/models.py
pyispyb/core/modules/__init__.py
pyispyb/core/modules/api.py
pyispyb/core/modules/auto_proc.py
pyispyb/core/modules/beamline_setup.py
pyispyb/core/modules/component.py
pyispyb/core/modules/contacts.py
pyispyb/core/modules/container.py
pyispyb/core/modules/crystal.py
pyispyb/core/modules/data_collection.py
pyispyb/core/modules/detector.py
pyispyb/core/modules/dewar.py
pyispyb/core/modules/diffraction_plan.py
pyispyb/core/modules/energy_scan.py
pyispyb/core/modules/image_quality_indicators.py
pyispyb/core/modules/proposal.py
pyispyb/core/modules/protein.py
pyispyb/core/modules/robot_action.py
pyispyb/core/modules/sample.py
pyispyb/core/modules/screening.py
pyispyb/core/modules/session.py
pyispyb/core/modules/shipping.py
pyispyb/core/routes/__init__.py
pyispyb/core/routes/auto_proc.py
pyispyb/core/routes/beamline.py
pyispyb/core/routes/contacts.py
pyispyb/core/routes/data_collections.py
pyispyb/core/routes/proposals.py
pyispyb/core/routes/samples.py
pyispyb-1.0.0.dist-info/LICENSE.md
pyispyb-1.0.0.dist-info/METADATA
pyispyb-1.0.0.dist-info/WHEEL
pyispyb-1.0.0.dist-info/top_level.txt
pyispyb-1.0.0.dist-info/RECORD
