Metadata-Version: 2.1
Name: pyispyb
Version: 1.0.0
Summary: ISPyB backend server
Home-page: https://github.com/ispyb/py-ispyb
Author: ISPyB collaboration
Author-email: ispyb-dev@esrf.fr
License: LGPL-3.0
Platform: UNKNOWN
Requires-Python: >=3.6
